environs_os_getter_class/__init__.py
environs_os_getter_class/main.py
environs_os_getter_class-0.0.2.dist-info/LICENSE
environs_os_getter_class-0.0.2.dist-info/METADATA
environs_os_getter_class-0.0.2.dist-info/WHEEL
environs_os_getter_class-0.0.2.dist-info/top_level.txt
environs_os_getter_class-0.0.2.dist-info/RECORD
