Metadata-Version: 2.1
Name: environs_os_getter_class
Version: 0.0.2
Summary: Update class attributes from Os Environment
Home-page: https://github.com/centroid457/environs_os_getter_class
Author: Andrei Starichenko
Author-email: centroid@mail.ru
Project-URL: Source, https://github.com/centroid457/environs_os_getter_class
Keywords: environs environment
Classifier: Development Status :: 5 - Production/Stable
Classifier: Programming Language :: Python
Classifier: Programming Language :: Python :: 3.11
Classifier: Operating System :: OS Independent
Classifier: Intended Audience :: Developers
Classifier: Natural Language :: English
Classifier: License :: OSI Approved :: MIT License
Requires-Python: >=3.6
License-File: LICENSE
